kvack/__init__.py
kvack/cli.py
kvack-0.1.0.dist-info/AUTHORS.rst
kvack-0.1.0.dist-info/LICENSE
kvack-0.1.0.dist-info/METADATA
kvack-0.1.0.dist-info/WHEEL
kvack-0.1.0.dist-info/entry_points.txt
kvack-0.1.0.dist-info/top_level.txt
kvack-0.1.0.dist-info/RECORD
