Metadata-Version: 2.1
Name: kvack
Version: 0.1.0
Summary: Tool configuration manager
Home-page: https://github.com/radowit/kvack
Author: Radosław Ganczarek
Author-email: radoslaw@ganczarek.in
License: BSD license
Keywords: kvack
Platform: UNKNOWN
Classifier: Development Status :: 2 - Pre-Alpha
Classifier: Intended Audience :: Developers
Classifier: License :: OSI Approved :: BSD License
Classifier: Natural Language :: English
Classifier: Programming Language :: Python :: 3
Classifier: Programming Language :: Python :: 3.9
Requires-Python: >=3.9
License-File: LICENSE
License-File: AUTHORS.rst
Requires-Dist: click (>=7.1.2)
Requires-Dist: toml (==0.10.2)
